repyexe/__init__.py
repyexe/__main__.py
repyexe/bytecode_graph.py
repyexe/clean.py
repyexe/decompile.py
repyexe/magic.py
repyexe/pyinstxtractor.py
repyexe/utilities.py
repyexe-0.1.3.dist-info/METADATA
repyexe-0.1.3.dist-info/WHEEL
repyexe-0.1.3.dist-info/entry_points.txt
repyexe-0.1.3.dist-info/top_level.txt
repyexe-0.1.3.dist-info/RECORD
