Metadata-Version: 2.1
Name: repyexe
Version: 0.1.3
Summary: Reverse engineer Windows executable file compiled using Python
Home-page: https://github.com/tangboxuan/reverse-python-exe
Author: Boxuan Tang
Author-email: tangboxuan@gmail.com
Keywords: reverse engineer windows executable python malware analysis
Classifier: Natural Language :: English
Classifier: Programming Language :: Python :: 2
Classifier: Programming Language :: Python :: 3
Classifier: Operating System :: OS Independent
Requires-Dist: pefile
Requires-Dist: uncompyle6
